mymoviebook/__init__.py
mymoviebook/devscripts.py
mymoviebook/images/mymoviebook.png
mymoviebook/images/mymoviebook_doxygen.png
mymoviebook/locale/es/LC_MESSAGES/mymoviebook.mo
mymoviebook/locale/es.po
mymoviebook/locale/fr/LC_MESSAGES/mymoviebook.mo
mymoviebook/locale/fr.po
mymoviebook/locale/mymoviebook.pot
mymoviebook/migrations/0001_initial.py
mymoviebook/migrations/0002_alter_covers_id.py
mymoviebook/migrations/0003_delete_globals.py
mymoviebook/migrations/0004_rename_id_films_films_id_remove_films_name_and_more.py
mymoviebook/migrations/0005_alter_films_id.py
mymoviebook/migrations/0006_rename_id_dvd_films_dvd.py
mymoviebook/migrations/0007_alter_covers_films_id.py
mymoviebook/migrations/0008_rename_films_id_covers_films.py
mymoviebook/migrations/0009_remove_covers_id_alter_covers_films.py
mymoviebook/migrations/__init__.py
mymoviebook/models.py
mymoviebook/mymoviebook.py
mymoviebook/reusing/casts.py
mymoviebook/reusing/github.py
mymoviebook/reusing/text_inputs.py
mymoviebook/settings.py
mymoviebook/sql/mymoviebook.sql
mymoviebook/sql/update_sql_dir.sh
mymoviebook-1.12.0.dist-info/LICENSE
mymoviebook-1.12.0.dist-info/METADATA
mymoviebook-1.12.0.dist-info/WHEEL
mymoviebook-1.12.0.dist-info/entry_points.txt
mymoviebook-1.12.0.dist-info/RECORD
