Metadata-Version: 2.1
Name: mymoviebook
Version: 1.12.0
Summary: Generate your personal movie collection book
License: GPL-3.0 license
Author: turulomio
Author-email: turulomio@yahoo.es
Requires-Python: >=3.10
Classifier: License :: Other/Proprietary License
Classifier: Programming Language :: Python :: 3
Classifier: Programming Language :: Python :: 3.10
Classifier: Programming Language :: Python :: 3.11
Classifier: Programming Language :: Python :: 3.12
Requires-Dist: colorama (>=0.4.6)
Requires-Dist: dj-database-url (>=1.3.0)
Requires-Dist: django (>=4.2)
Requires-Dist: platformdirs (>=3.2.0)
Requires-Dist: psycopg2 (>=2.9.6)
Requires-Dist: python-decouple (>=3.8)
Requires-Dist: tqdm (>=4.65.0)
